simple_rsync/__init__.py
simple_rsync/__version__.py
simple_rsync/simple_rsync.cp312-win_amd64.pyd
simple_rsync-1.0.1.dist-info/LICENSE
simple_rsync-1.0.1.dist-info/METADATA
simple_rsync-1.0.1.dist-info/WHEEL
simple_rsync-1.0.1.dist-info/top_level.txt
simple_rsync-1.0.1.dist-info/RECORD
