Metadata-Version: 2.1
Name: simple-rsync
Version: 1.0.1
Summary: Simple Python interface for librsync
Home-page: https://github.com/YAtOff/simple-rsync
Author: Yavor Atov
Author-email: yavor.atov@gmail.com
License: Apache
Classifier: License :: OSI Approved :: Apache Software License
Classifier: Development Status :: 3 - Alpha
Classifier: Intended Audience :: Developers
Classifier: Programming Language :: Python
Classifier: Programming Language :: Rust
Requires-Python: >=3.7
License-File: LICENSE
